{
  "generatedAt": "2026-01-25T15:11:22.411Z",
  "source": "kudosprime.com",
  "game": "fh5",
  "items": [
    {
      "id": "1",
      "url": "https://www.kudosprime.com/fh5/car_sheet.php?id=1",
      "identity": {
        "year": "2001",
        "make": "Acura",
        "model": null
      },
      "carImages": [
        {
          "src": "https://www.kudosprime.com/fh5/images/users/th/car_1_1_619956101a602.jpg",
          "alt": "",
          "title": "",
          "className": "",
          "naturalWidth": 119,
          "naturalHeight": 67
        },
        {
          "src": "https://www.kudosprime.com/fh5/images/users/th/car_1_1_61995610ecf12.jpg",
          "alt": "",
          "title": "",
          "className": "",
          "naturalWidth": 119,
          "naturalHeight": 67
        },
        {
          "src": "https://www.kudosprime.com/fh5/images/users/th/car_1_1_61995611d457b.jpg",
          "alt": "",
          "title": "",
          "className": "",
          "naturalWidth": 119,
          "naturalHeight": 67
        },
        {
          "src": "https://www.kudosprime.com/fh5/images/users/th/car_1_64649_61ac0de057716.jpg",
          "alt": "",
          "title": "",
          "className": "",
          "naturalWidth": 120,
          "naturalHeight": 50
        },
        {
          "src": "https://www.kudosprime.com/fh5/images/users/th/car_1_77989_6227ea167df19.jpg",
          "alt": "",
          "title": "",
          "className": "",
          "naturalWidth": 119,
          "naturalHeight": 67
        },
        {
          "src": "https://www.kudosprime.com/fh5/images/users/th/car_1_89307_6542c6fa32368.jpg",
          "alt": "",
          "title": "",
          "className": "",
          "naturalWidth": 119,
          "naturalHeight": 67
        },
        {
          "src": "https://www.kudosprime.com/fh5/images/users/th/car_1_101493_675e14de443a8.jpg",
          "alt": "",
          "title": "",
          "className": "",
          "naturalWidth": 119,
          "naturalHeight": 67
        }
      ],
      "carImageUrls": [
        "https://www.kudosprime.com/fh5/images/cars/big/fh5_car_001.jpg",
        "../images/flags/main/usa.png",
        "images/users/th/car_1_1_619956101a602.jpg",
        "images/users/th/car_1_1_61995610ecf12.jpg",
        "images/users/th/car_1_1_61995611d457b.jpg",
        "images/users/th/car_1_64649_61ac0de057716.jpg",
        "images/users/th/car_1_77989_6227ea167df19.jpg",
        "images/users/th/car_1_89307_6542c6fa32368.jpg",
        "images/users/th/car_1_101493_675e14de443a8.jpg",
        "images/milouse_50x100.png",
        "/images/flags/main/chile.png"
      ],
      "rawTextSample": "Forza Motorsport\nF7\nF6\nF5\nF4\nF3\nF. Horizon 5\nFH4\nFH3\nFH2\nFH\nGran Turismo 7\nGTS\nGT6\nGT5\nNFS MW\nGTA 5\nNot connected\nSign in\nNew account\nContact\nhome\nmap250 Boards\ndrive_etaCars\nstarsPerks\ntrending_upStats\npublicExport\nsearch\ndrive_eta\nKudosprime // FH5 Car Database // Acura\n\n 2001 Acura\n\nIntegra Type-R\n\nadd_a_photo\nAdd your own FH5 photo(s) for this car.\n\nAcura Integra\n\nAlternate Name(s)\n\nOther Acura cars\n2017 NSX\n2002 RSX Type-S\nIf you want to contact me about Forza Horizon 5 on K', you can use the Contact button on top of the current page. Milouse\n \n25,000 Cr\nRETRO HOT HATCH\nC\n596\ncall_made\nS2\n922\nMAX\n195HP FWD 2639lbs 0.074HP/lbs -10.1%\n\nAutoshow & Wheelspin\n5.6SPEED+0.2\n4.6HANDLING+0.4\n3.9ACCELERATION-0.4\n3.1LAUNCH-0.6\n3.4BRAKING\n5.4OFFROAD-0.6\n\nTop Speed:155.5 Mph+5.1% Lat. G @60 Mph:0.90+3.4%\n\n0 to...60 Mph:6.216 s-2.1% 100 Mph:14.716 s-8.2%\n\nLateral G@60 Mph:0.90+3.4%\n\nData compared to 29 cars from PI 586 to PI 606\n\nCar data contributors: jxm040 walslayer Milouse FH5GAMER Oween\nLink to this car in all Forza games since 2009:\nFM\tFH5\tFH4\tF7\tFH3\tF6\tFH2XO\tF5\tFH\tF4\tF3\n10\t1\t85\t566\t182\t6\t257\t3\t-\t86\t96\n\nCar Masteries\n\nList cars having the exact same Car Mastery grid (non-exhaustive)\n20\n5 p\n20\n5 p\n20\n5 p\n20\n5 p\n10\n3 p\n15\n3 p\n1.5\n3 p\n20\n3 p\n25 p\n5\n1 p\n0.5\n1 p\n2000\n1 p\n+20 % XP for the next 10 street races\n5 sp\nDaredevil Skill Score: +20 %\n5 sp\n+20 % XP from banked Skills in Freeroam\n5 sp\nDrift and E-Drift Skill Score: +20 %\n5 sp\nInstant 10 Forza Points\n3 sp\nPermanent +15 % in Event Finish XP\n3 sp\nSkill Multiplier built 1.5 times faster during Skill Songs\n3 sp\nHead-to-Head Credits: +20 %\n3 sp\nThe first collision doesn't break the current Skill Chain\n25 sp\nPass Skill Score: +5 %\n1 sp\nSkill Chains ends 0.5 second later\n1 sp\nInstant 2000 XP\n1 sp\n You need to be connected to post comment\nmessage #2 | Sunday September 04, 2022 | RageMix  | Report\nPass Skill Score +5% changes to Extra 5% XP for 10 Drag Racing Events.\n \nCopyright 2010-2026 KudosPrime.com. \"Forza Motorsport\" is a trademark of Microsoft    u(0.0001) a(0.0253) m(943K) l(2592000) 2fr - Privacy Policy\n\nhelper text"
    },
    {
      "id": "2",
      "url": "https://www.kudosprime.com/fh5/car_sheet.php?id=2",
      "identity": {
        "year": "2002",
        "make": "Acura",
        "model": null
      },
      "carImages": [
        {
          "src": "https://www.kudosprime.com/fh5/images/users/th/car_2_64649_61ac0f012aaec.jpg",
          "alt": "",
          "title": "",
          "className": "",
          "naturalWidth": 120,
          "naturalHeight": 50
        },
        {
          "src": "https://www.kudosprime.com/fh5/images/users/th/car_2_77989_6227ea227356e.jpg",
          "alt": "",
          "title": "",
          "className": "",
          "naturalWidth": 119,
          "naturalHeight": 67
        },
        {
          "src": "https://www.kudosprime.com/fh5/images/users/th/car_2_77989_6227ea297854c.jpg",
          "alt": "",
          "title": "",
          "className": "",
          "naturalWidth": 119,
          "naturalHeight": 67
        },
        {
          "src": "https://www.kudosprime.com/fh5/images/users/th/car_2_89307_6542c74e42d4b.jpg",
          "alt": "",
          "title": "",
          "className": "",
          "naturalWidth": 119,
          "naturalHeight": 67
        },
        {
          "src": "https://www.kudosprime.com/fh5/images/users/th/car_2_102477_66fa9dcf5fade.jpg",
          "alt": "",
          "title": "",
          "className": "",
          "naturalWidth": 119,
          "naturalHeight": 67
        },
        {
          "src": "https://www.kudosprime.com/fh5/images/users/th/car_2_102477_66fa9dcff3254.jpg",
          "alt": "",
          "title": "",
          "className": "",
          "naturalWidth": 119,
          "naturalHeight": 67
        },
        {
          "src": "https://www.kudosprime.com/fh5/images/users/th/car_2_102477_66fa9dd095c85.jpg",
          "alt": "",
          "title": "",
          "className": "",
          "naturalWidth": 119,
          "naturalHeight": 67
        },
        {
          "src": "https://www.kudosprime.com/fh5/images/users/th/car_2_102564_6726741f09ed8.jpg",
          "alt": "",
          "title": "",
          "className": "",
          "naturalWidth": 120,
          "naturalHeight": 53
        },
        {
          "src": "https://www.kudosprime.com/fh5/images/users/th/car_2_101493_675e151ac28e0.jpg",
          "alt": "",
          "title": "",
          "className": "",
          "naturalWidth": 119,
          "naturalHeight": 67
        },
        {
          "src": "https://www.kudosprime.com/fh5/images/users/th/car_2_104282_692ac88f2dd67.jpg",
          "alt": "",
          "title": "",
          "className": "",
          "naturalWidth": 119,
          "naturalHeight": 67
        },
        {
          "src": "https://www.kudosprime.com/fh5/images/users/th/car_2_104282_692ac897ac17c.jpg",
          "alt": "",
          "title": "",
          "className": "",
          "naturalWidth": 119,
          "naturalHeight": 67
        },
        {
          "src": "https://www.kudosprime.com/fh5/images/users/th/car_2_108158_6959a275f3372.jpg",
          "alt": "",
          "title": "",
          "className": "",
          "naturalWidth": 119,
          "naturalHeight": 67
        }
      ],
      "carImageUrls": [
        "https://www.kudosprime.com/fh5/images/cars/big/fh5_car_002.jpg",
        "https://connect.facebook.net/rsrc.php/v4/yq/r/IE9JII6Z1Ys.png",
        "https://connect.facebook.net/rsrc.php/v4/yq/r/IE9JII6Z1Ys.png",
        "https://connect.facebook.net/rsrc.php/v4/yq/r/IE9JII6Z1Ys.png",
        "https://connect.facebook.net/rsrc.php/v4/yd/r/Cou7n-nqK52.gif",
        "https://connect.facebook.net/rsrc.php/v4/ya/r/3rhSv5V8j3o.gif",
        "https://connect.facebook.net/rsrc.php/v4/y9/r/jKEcVPZFk-2.gif",
        "https://connect.facebook.net/rsrc.php/v4/y2/r/onuUJj0tCqE.png",
        "../images/flags/main/usa.png",
        "images/users/th/car_2_64649_61ac0f012aaec.jpg",
        "images/users/th/car_2_77989_6227ea227356e.jpg",
        "images/users/th/car_2_77989_6227ea297854c.jpg",
        "images/users/th/car_2_89307_6542c74e42d4b.jpg",
        "images/users/th/car_2_102477_66fa9dcf5fade.jpg",
        "images/users/th/car_2_102477_66fa9dcff3254.jpg",
        "images/users/th/car_2_102477_66fa9dd095c85.jpg",
        "images/users/th/car_2_102564_6726741f09ed8.jpg",
        "images/users/th/car_2_101493_675e151ac28e0.jpg",
        "images/users/th/car_2_104282_692ac88f2dd67.jpg",
        "images/users/th/car_2_104282_692ac897ac17c.jpg",
        "images/users/th/car_2_108158_6959a275f3372.jpg",
        "images/milouse_50x100.png",
        "/images/flags/main/chile.png"
      ],
      "rawTextSample": "Good news : we're only using non intrusive, necessary cookies. Learn more\nGot it!\nForza Motorsport\nF7\nF6\nF5\nF4\nF3\nF. Horizon 5\nFH4\nFH3\nFH2\nFH\nGran Turismo 7\nGTS\nGT6\nGT5\nNFS MW\nGTA 5\nNot connected\nSign in\nNew account\nContact\nhome\nmap250 Boards\ndrive_etaCars\nstarsPerks\ntrending_upStats\npublicExport\nsearch\ndrive_eta\nKudosprime // FH5 Car Database // Acura\n\n 2002 Acura\n\nRSX Type-S\n\nadd_a_photo\nAdd your own FH5 photo(s) for this car.\n\nAcura RSX\n\nAlternate Name(s)\n\nOther Acura cars\n2017 NSX\n2001 Integra Type-R\nIf you want to contact me about Forza Horizon 5 on K', you can use the Contact button on top of the current page. Milouse\n \n25,000 Cr\nRETRO HOT HATCH\nC\n585\ncall_made\nS2\n906\nMAX\n200HP FWD 2820lbs 0.071HP/lbs -12.3%\n\nAutoshow & Wheelspin\n5.6SPEED+0.3\n4.7HANDLING+0.4\n3.9ACCELERATION-0.3\n3.0LAUNCH-0.6\n3.5BRAKING+0.2\n5.6OFFROAD-0.3\n\nTop Speed:148.4 Mph+2.1% Lat. G @60 Mph:0.90+3.4%\n\n0 to...60 Mph:6.717 s+5.8% 100 Mph:18.019 s+9.7%\n\nLateral G@60 Mph:0.90+3.4%\n\nData compared to 28 cars from PI 575 to PI 595\n\nCar data contributors: jxm040 walslayer Milouse MarkinoVak KZ Pluto\nLink to this car in all Forza games since 2009:\nFM\tFH5\tFH4\tF7\tFH3\tF6\tFH2XO\tF5\tFH\tF4\tF3\n-\t2\t264\t342\t172\t5\t153\t2\t-\t83\t57\n\nCar Masteries\n\nList cars having the exact same Car Mastery grid (non-exhaustive)\n20\n5 p\n20\n5 p\n20\n5 p\n20\n5 p\n10\n3 p\n15\n3 p\n1.5\n3 p\n20\n3 p\n25 p\n5\n1 p\n0.5\n1 p\n2000\n1 p\n+20 % XP for the next 10 street races\n5 sp\nDaredevil Skill Score: +20 %\n5 sp\n+20 % XP from banked Skills in Freeroam\n5 sp\nDrift and E-Drift Skill Score: +20 %\n5 sp\nInstant 10 Forza Points\n3 sp\nPermanent +15 % in Event Finish XP\n3 sp\nSkill Multiplier built 1.5 times faster during Skill Songs\n3 sp\nHead-to-Head Credits: +20 %\n3 sp\nThe first collision doesn't break the current Skill Chain\n25 sp\nPass Skill Score: +5 %\n1 sp\nSkill Chains ends 0.5 second later\n1 sp\nInstant 2000 XP\n1 sp\n You need to be connected to post comment\nmessage #2 | Sunday September 04, 2022 | RageMix  | Report\nPass Skill Score +5% changes to Extra 5% XP for 10 Drag Racing Events.\n \nCopyright 2010-2026 KudosPrime.com. \"Forza Motorsport\" is a trademark of Microsoft    u(0) a(0.0218) m(952K) l(2592000) 2fr - Privacy Policy\n\nhelper text"
    },
    {
      "id": "3",
      "url": "https://www.kudosprime.com/fh5/car_sheet.php?id=3",
      "identity": {
        "year": "2017",
        "make": "Acura",
        "model": "Acura NSX"
      },
      "carImages": [
        {
          "src": "https://www.kudosprime.com/fh5/images/users/th/car_3_64649_61ac0b7f0e136.jpg",
          "alt": "",
          "title": "",
          "className": "",
          "naturalWidth": 120,
          "naturalHeight": 50
        },
        {
          "src": "https://www.kudosprime.com/fh5/images/users/th/car_3_77989_6330d0f2b214c.jpg",
          "alt": "",
          "title": "",
          "className": "",
          "naturalWidth": 119,
          "naturalHeight": 67
        },
        {
          "src": "https://www.kudosprime.com/fh5/images/users/th/car_3_77989_6539c5bb894d2.jpg",
          "alt": "",
          "title": "",
          "className": "",
          "naturalWidth": 119,
          "naturalHeight": 67
        },
        {
          "src": "https://www.kudosprime.com/fh5/images/users/th/car_3_89307_6542c7b4c1c36.jpg",
          "alt": "",
          "title": "",
          "className": "",
          "naturalWidth": 119,
          "naturalHeight": 67
        },
        {
          "src": "https://www.kudosprime.com/fh5/images/users/th/car_3_102539_670272960339d.jpg",
          "alt": "",
          "title": "",
          "className": "",
          "naturalWidth": 119,
          "naturalHeight": 67
        },
        {
          "src": "https://www.kudosprime.com/fh5/images/users/th/car_3_101493_675e14f0af128.jpg",
          "alt": "",
          "title": "",
          "className": "",
          "naturalWidth": 119,
          "naturalHeight": 67
        },
        {
          "src": "https://www.kudosprime.com/fh5/images/users/th/car_3_108158_6959a0f4c1061.jpg",
          "alt": "",
          "title": "",
          "className": "",
          "naturalWidth": 119,
          "naturalHeight": 67
        }
      ],
      "carImageUrls": [
        "https://www.kudosprime.com/fh5/images/cars/big/fh5_car_003.jpg",
        "../images/flags/main/usa.png",
        "images/users/th/car_3_64649_61ac0b7f0e136.jpg",
        "images/users/th/car_3_77989_6330d0f2b214c.jpg",
        "images/users/th/car_3_77989_6539c5bb894d2.jpg",
        "images/users/th/car_3_89307_6542c7b4c1c36.jpg",
        "images/users/th/car_3_102539_670272960339d.jpg",
        "images/users/th/car_3_101493_675e14f0af128.jpg",
        "images/users/th/car_3_108158_6959a0f4c1061.jpg",
        "images/milouse_50x100.png"
      ],
      "rawTextSample": "Forza Motorsport\nF7\nF6\nF5\nF4\nF3\nF. Horizon 5\nFH4\nFH3\nFH2\nFH\nGran Turismo 7\nGTS\nGT6\nGT5\nNFS MW\nGTA 5\nNot connected\nSign in\nNew account\nContact\nhome\nmap250 Boards\ndrive_etaCars\nstarsPerks\ntrending_upStats\npublicExport\nsearch\ndrive_eta\nKudosprime // FH5 Car Database // Acura\n\n 2017 Acura\n\nNSX\n\nadd_a_photo\nAdd your own FH5 photo(s) for this car.\n\nAcura NSX '17\n\nAlternate Name(s)\n\nOther Acura cars\n2002 RSX Type-S\n2001 Integra Type-R\nIf you want to contact me about Forza Horizon 5 on K', you can use the Contact button on top of the current page. Milouse\n \n170,000 Cr\nMODERN SUPERCARS\nS1\n831\ncall_made\nS2\n959\nMAX\n573HP AWD 3803lbs 0.151HP/lbs -33.9%\n\nAutoshow & Wheelspin\n7.0SPEED-0.1\n6.3HANDLING+0.3\n9.2ACCELERATION+2.7\n10LAUNCH+3.8\n7.1BRAKING+0.9\n5.3OFFROAD+0.2\n\nTop Speed:193.4 Mph-1.1% Lat. G @60 Mph:1.10-0.9%\n\n0 to...60 Mph:2.700 s-21.6% 100 Mph:6.400 s-7.7%\n\nLateral G@60 Mph:1.10-0.9%\n\nData compared to 46 cars from PI 821 to PI 841\n\nCar data contributors: Milouse TitanNidoking MarkinoVak KZ Pluto Oween\nLink to this car in all Forza games since 2009:\nFM\tFH5\tFH4\tF7\tFH3\tF6\tFH2XO\tF5\tFH\tF4\tF3\n245\t3\t358\t375\t415\t-\t-\t-\t-\t-\t-\n\nCar Masteries\n\nList cars having the exact same Car Mastery grid (non-exhaustive)\n15\n10 p\n25\n10 p\n10000\n10 p\n20\n5 p\n20\n5 p\n20\n5 p\n15\n3 p\n15\n3 p\n15\n3 p\n15\n3 p\n25 p\n10\n1 p\n10\n1 p\n25000\n1 p\nInstant 15 Forza Points\n10 sp\nSpeed Skill Score: +25 %\n10 sp\nInstant 10000 XP\n10 sp\n+20 % XP from banked Skills in Freeroam\n5 sp\nTriple Pass Combo Skill Score: +20 %\n5 sp\nDaredevil Skill Score: +20 %\n5 sp\nPermanent +15 % in Event Finish XP\n3 sp\nSlingshot Skill Score: +15 %\n3 sp\nClean Racing Skill Score: +15 %\n3 sp\nDrafting Skill Score: +15 %\n3 sp\nThe first collision doesn't break the current Skill Chain\n25 sp\nLucky Escape Skill Score: +10 %\n1 sp\nHead-to-Head Credits: +10 %\n1 sp\nInstant 25000 Credits\n1 sp\n You need to be connected to post comment\n \nCopyright 2010-2026 KudosPrime.com. \"Forza Motorsport\" is a trademark of Microsoft    u(0.0001) a(0.0185) m(931K) l(2592000) 2fr - Privacy Policy\n\nhelper text"
    },
    {
      "id": "4",
      "url": "https://www.kudosprime.com/fh5/car_sheet.php?id=4",
      "identity": {
        "year": "1973",
        "make": "Alpine",
        "model": "Alpine A110"
      },
      "carImages": [
        {
          "src": "https://www.kudosprime.com/fh5/images/users/th/car_4_1_6196762de6baf.jpg",
          "alt": "",
          "title": "",
          "className": "",
          "naturalWidth": 119,
          "naturalHeight": 67
        },
        {
          "src": "https://www.kudosprime.com/fh5/images/users/th/car_4_77989_621ac68f9ce93.jpg",
          "alt": "",
          "title": "",
          "className": "",
          "naturalWidth": 119,
          "naturalHeight": 67
        },
        {
          "src": "https://www.kudosprime.com/fh5/images/users/th/car_4_77989_621ac6962e064.jpg",
          "alt": "",
          "title": "",
          "className": "",
          "naturalWidth": 119,
          "naturalHeight": 67
        },
        {
          "src": "https://www.kudosprime.com/fh5/images/users/th/car_4_1_640a0a4943606.jpg",
          "alt": "",
          "title": "",
          "className": "",
          "naturalWidth": 119,
          "naturalHeight": 67
        },
        {
          "src": "https://www.kudosprime.com/fh5/images/users/th/car_4_101493_675e15d4a8a05.jpg",
          "alt": "",
          "title": "",
          "className": "",
          "naturalWidth": 119,
          "naturalHeight": 67
        }
      ],
      "carImageUrls": [
        "https://www.kudosprime.com/fh5/images/cars/big/fh5_car_004.jpg",
        "https://connect.facebook.net/rsrc.php/v4/yq/r/IE9JII6Z1Ys.png",
        "https://connect.facebook.net/rsrc.php/v4/yq/r/IE9JII6Z1Ys.png",
        "https://connect.facebook.net/rsrc.php/v4/yq/r/IE9JII6Z1Ys.png",
        "https://connect.facebook.net/rsrc.php/v4/yd/r/Cou7n-nqK52.gif",
        "https://connect.facebook.net/rsrc.php/v4/ya/r/3rhSv5V8j3o.gif",
        "https://connect.facebook.net/rsrc.php/v4/y9/r/jKEcVPZFk-2.gif",
        "https://connect.facebook.net/rsrc.php/v4/y2/r/onuUJj0tCqE.png",
        "../images/flags/main/france.png",
        "images/users/th/car_4_1_6196762de6baf.jpg",
        "images/users/th/car_4_77989_621ac68f9ce93.jpg",
        "images/users/th/car_4_77989_621ac6962e064.jpg",
        "images/users/th/car_4_1_640a0a4943606.jpg",
        "images/users/th/car_4_101493_675e15d4a8a05.jpg",
        "images/milouse_50x100.png",
        "/images/flags/main/chile.png"
      ],
      "rawTextSample": "Good news : we're only using non intrusive, necessary cookies. Learn more\nGot it!\nForza Motorsport\nF7\nF6\nF5\nF4\nF3\nF. Horizon 5\nFH4\nFH3\nFH2\nFH\nGran Turismo 7\nGTS\nGT6\nGT5\nNFS MW\nGTA 5\nNot connected\nSign in\nNew account\nContact\nhome\nmap250 Boards\ndrive_etaCars\nstarsPerks\ntrending_upStats\npublicExport\nsearch\ndrive_eta\nKudosprime // FH5 Car Database // Alpine\n\n 1973 Alpine\n\nA110 1600s\n\nadd_a_photo\nAdd your own FH5 photo(s) for this car.\n\nAlpine A110 '73\n\nAlternate Name(s)\n\nOther Alpine cars\n2017 A110\nIf you want to contact me about Forza Horizon 5 on K', you can use the Contact button on top of the current page. Milouse\n \n98,000 Cr\nCLASSIC RALLY\nC\n550\ncall_made\nS2\n936\nMAX\n123HP RWD 1576lbs 0.078HP/lbs -9.3%\n\nAutoshow & Wheelspin\n5.0SPEED-0.3\n4.1HANDLING+0.2\n4.1ACCELERATION+0.3\n3.1LAUNCH-0.1\n3.0BRAKING+0.2\n5.5OFFROAD-0.3\n\nTop Speed:138.0 Mph-5.6% Lat. G @60 Mph:0.84+2.4%\n\n0 to...60 Mph:6.974 s+5.7% 100 Mph:20.684 s+22.9%\n\nLateral G@60 Mph:0.84+2.4%\n\nData compared to 35 cars from PI 540 to PI 560\n\nCar data contributors: jxm040 walslayer Milouse MarkinoVak groenroos Oween\nLink to this car in all Forza games since 2009:\nFM\tFH5\tFH4\tF7\tFH3\tF6\tFH2XO\tF5\tFH\tF4\tF3\n-\t4\t-\t-\t-\t-\t-\t-\t-\t-\t-\n\nCar Masteries\n\nList cars having the exact same Car Mastery grid (non-exhaustive)\n25\n10 p\n20\n5 p\n20\n5 p\n20\n5 p\n10\n3 p\n15\n3 p\n15\n3 p\n25 p\n10000\n1 p\n5\n1 p\n3000\n1 p\n+25 % XP for the next 10 road races\n10 sp\n+20 % XP for the next 10 Dirt Racing events\n5 sp\nCombo Skill Score: +20 %\n5 sp\nPass Skill Score: +20 %\n5 sp\nInstant 10 Forza Points\n3 sp\nSpeed Skill Score: +15 %\n3 sp\nAir Skill Score: +15 %\n3 sp\nThe first collision doesn't break the current Skill Chain\n25 sp\nInstant 10000 Credits\n1 sp\nPermanent +5 % in Event Finish XP\n1 sp\nInstant 3000 XP\n1 sp\n You need to be connected to post comment\nmessage #1 | Sunday September 04, 2022 | RageMix  | Report\n- Reduced Perk 1; From 4000 to 3000 XP.\n- Wheelspin changed to 10 FP\n\n \nCopyright 2010-2026 KudosPrime.com. \"Forza Motorsport\" is a trademark of Microsoft    u(0.0001) a(0.0192) m(938K) l(2592000) 2fr - Privacy Policy\n\nhelper text"
    },
    {
      "id": "5",
      "url": "https://www.kudosprime.com/fh5/car_sheet.php?id=5",
      "identity": {
        "year": "2017",
        "make": "Alpine",
        "model": "Alpine A110"
      },
      "carImages": [
        {
          "src": "https://www.kudosprime.com/fh5/images/users/th/car_5_49807_6192c759bcd4c.jpg",
          "alt": "",
          "title": "",
          "className": "",
          "naturalWidth": 119,
          "naturalHeight": 67
        },
        {
          "src": "https://www.kudosprime.com/fh5/images/users/th/car_5_49807_6192c75a0f837.jpg",
          "alt": "",
          "title": "",
          "className": "",
          "naturalWidth": 119,
          "naturalHeight": 67
        },
        {
          "src": "https://www.kudosprime.com/fh5/images/users/th/car_5_1_619caa7454ed1.jpg",
          "alt": "",
          "title": "",
          "className": "",
          "naturalWidth": 119,
          "naturalHeight": 67
        },
        {
          "src": "https://www.kudosprime.com/fh5/images/users/th/car_5_1_619caa752d928.jpg",
          "alt": "",
          "title": "",
          "className": "",
          "naturalWidth": 119,
          "naturalHeight": 67
        },
        {
          "src": "https://www.kudosprime.com/fh5/images/users/th/car_5_1_619caa7604ec6.jpg",
          "alt": "",
          "title": "",
          "className": "",
          "naturalWidth": 119,
          "naturalHeight": 67
        },
        {
          "src": "https://www.kudosprime.com/fh5/images/users/th/car_5_77989_62254b4971362.jpg",
          "alt": "",
          "title": "",
          "className": "",
          "naturalWidth": 119,
          "naturalHeight": 67
        },
        {
          "src": "https://www.kudosprime.com/fh5/images/users/th/car_5_77989_62254b5114064.jpg",
          "alt": "",
          "title": "",
          "className": "",
          "naturalWidth": 119,
          "naturalHeight": 67
        },
        {
          "src": "https://www.kudosprime.com/fh5/images/users/th/car_5_77989_62254b59d70e3.jpg",
          "alt": "",
          "title": "",
          "className": "",
          "naturalWidth": 119,
          "naturalHeight": 67
        },
        {
          "src": "https://www.kudosprime.com/fh5/images/users/th/car_5_77989_62254b5e2cce5.jpg",
          "alt": "",
          "title": "",
          "className": "",
          "naturalWidth": 119,
          "naturalHeight": 67
        },
        {
          "src": "https://www.kudosprime.com/fh5/images/users/th/car_5_101493_675e15c10a3e5.jpg",
          "alt": "",
          "title": "",
          "className": "",
          "naturalWidth": 119,
          "naturalHeight": 67
        }
      ],
      "carImageUrls": [
        "https://www.kudosprime.com/fh5/images/cars/big/fh5_car_005.jpg",
        "https://connect.facebook.net/rsrc.php/v4/yq/r/IE9JII6Z1Ys.png",
        "https://connect.facebook.net/rsrc.php/v4/yq/r/IE9JII6Z1Ys.png",
        "https://connect.facebook.net/rsrc.php/v4/yq/r/IE9JII6Z1Ys.png",
        "https://connect.facebook.net/rsrc.php/v4/yd/r/Cou7n-nqK52.gif",
        "https://connect.facebook.net/rsrc.php/v4/ya/r/3rhSv5V8j3o.gif",
        "https://connect.facebook.net/rsrc.php/v4/y9/r/jKEcVPZFk-2.gif",
        "https://connect.facebook.net/rsrc.php/v4/y2/r/onuUJj0tCqE.png",
        "../images/flags/main/france.png",
        "images/users/th/car_5_49807_6192c759bcd4c.jpg",
        "images/users/th/car_5_49807_6192c75a0f837.jpg",
        "images/users/th/car_5_1_619caa7454ed1.jpg",
        "images/users/th/car_5_1_619caa752d928.jpg",
        "images/users/th/car_5_1_619caa7604ec6.jpg",
        "images/users/th/car_5_77989_62254b4971362.jpg",
        "images/users/th/car_5_77989_62254b5114064.jpg",
        "images/users/th/car_5_77989_62254b59d70e3.jpg",
        "images/users/th/car_5_77989_62254b5e2cce5.jpg",
        "images/users/th/car_5_101493_675e15c10a3e5.jpg",
        "images/milouse_50x100.png",
        "/images/flags/main/italy.png",
        "/images/flags/main/usa.png"
      ],
      "rawTextSample": "Good news : we're only using non intrusive, necessary cookies. Learn more\nGot it!\nForza Motorsport\nF7\nF6\nF5\nF4\nF3\nF. Horizon 5\nFH4\nFH3\nFH2\nFH\nGran Turismo 7\nGTS\nGT6\nGT5\nNFS MW\nGTA 5\nNot connected\nSign in\nNew account\nContact\nhome\nmap250 Boards\ndrive_etaCars\nstarsPerks\ntrending_upStats\npublicExport\nsearch\ndrive_eta\nKudosprime // FH5 Car Database // Alpine\n\n 2017 Alpine\n\nA110\n\nadd_a_photo\nAdd your own FH5 photo(s) for this car.\n\nAlpine A110 '17\n\nAlternate Name(s)\n\nOther Alpine cars\n1973 A110 1600s\nIf you want to contact me about Forza Horizon 5 on K', you can use the Contact button on top of the current page. Milouse\n \n67,500 Cr\nMODERN SPORTS CARS\nB\n694\ncall_made\nS2\n926\nMAX\n248HP RWD 2432lbs 0.102HP/lbs -3.3%\n\nSeason Event\nFestival Playlist\nForza Shop\nBackstage Pass\n6.0SPEED\n5.8HANDLING+1\n5.4ACCELERATION+0.2\n5.7LAUNCH+0.9\n4.2BRAKING\n4.7OFFROAD-1.5\n\nTop Speed:164.0 Mph-0.4% Lat. G @60 Mph:0.98+4.3%\n\n0 to...60 Mph:4.300 s-8.4% 100 Mph:11.600 s+1.2%\n\nLateral G@60 Mph:0.98+4.3%\n\nData compared to 36 cars from PI 684 to PI 704\n\nCar data contributors: Milouse MarkinoVak KZ Pluto Oween\nLink to this car in all Forza games since 2009:\nFM\tFH5\tFH4\tF7\tFH3\tF6\tFH2XO\tF5\tFH\tF4\tF3\n232\t5\t662\t-\t-\t-\t-\t-\t-\t-\t-\n\nCar Masteries\n\nList cars having the exact same Car Mastery grid (non-exhaustive)\n1\n10 p\n2\n10 p\n20\n5 p\n150\n5 p\n20\n5 p\n10\n3 p\n15\n3 p\n20\n3 p\n15\n3 p\n25 p\n15000\n1 p\n10\n1 p\n4000\n1 p\nGet 1 Wheelspin\n10 sp\nSkill Multiplier built 2 times faster during Skill Songs\n10 sp\nClean Racing Skill Score: +20 %\n5 sp\nSkill points banked grants +150 % XP points for the next 10 campaign races\n5 sp\nUltimate Skill Chains score: +20 %\n5 sp\nInstant 10 Forza Points\n3 sp\nPermanent +15 % in Event Finish XP\n3 sp\nHead-to-Head Credits: +20 %\n3 sp\nDrafting Skill Score: +15 %\n3 sp\nThe first collision doesn't break the current Skill Chain\n25 sp\nInstant 15000 Credits\n1 sp\n+10 % XP from banked Skills in Freeroam\n1 sp\nInstant 4000 XP\n1 sp\n You need to be connected to post comment\nmessage #2 | Monday June 30, 2025 | Jeckhicks  | Report\nThis is a wheelspin car now.\nmessage #1 | Thursday September 29, 2022 | FH5GAMER  | Report\nThe model featured in the game is the Premiere Edition model, not that it reads it that way.\n \nCopyright 2010-2026 KudosPrime.com. \"Forza Motorsport\" is a trademark of Microsoft    u(0) a(0.0163) m(953K) l(2592000) 2fr - Privacy Policy\n\nhelper text"
    }
  ],
  "errors": []
}